pycarwings2/__init__.py
pycarwings2/pycarwings2.py
pycarwings2/responses.py
pycarwings2-2.14.dist-info/LICENSE
pycarwings2-2.14.dist-info/METADATA
pycarwings2-2.14.dist-info/WHEEL
pycarwings2-2.14.dist-info/top_level.txt
pycarwings2-2.14.dist-info/RECORD
