Metadata-Version: 2.1
Name: pycarwings2
Version: 2.14
Summary: Python library for interacting with the Nissan Leaf Carwings telematics service
Home-page: https://github.com/filcole/pycarwings2
Author: Phil Cole
Author-email: filcole@gmail.com
License: Apache Software License
Keywords: nissan leaf carwings nissan+you
Platform: UNKNOWN
Classifier: Development Status :: 4 - Beta
Classifier: Intended Audience :: Developers
Classifier: License :: OSI Approved :: Apache Software License
Classifier: Programming Language :: Python :: 3.5
Classifier: Programming Language :: Python :: 3.6
Classifier: Programming Language :: Python :: 3.7
Classifier: Programming Language :: Python :: 3.8
Classifier: Programming Language :: Python :: 3.9
Classifier: Programming Language :: Python :: 3 :: Only
License-File: LICENSE
